pyqtgameboards/__init__.py
pyqtgameboards/gameboard.py
pyqt_gameboard-0.2.6.dist-info/LICENSE
pyqt_gameboard-0.2.6.dist-info/METADATA
pyqt_gameboard-0.2.6.dist-info/WHEEL
pyqt_gameboard-0.2.6.dist-info/top_level.txt
pyqt_gameboard-0.2.6.dist-info/RECORD
