Metadata-Version: 2.1
Name: pyqt-gameboard
Version: 0.2.6
Summary: A gameboard widget for pyqt gui's package
Home-page: https://github.com/Michael-Yongshi/PyQtGameBoard
Author: Michael-Yongshi
Author-email: 4registration@outlook.com
License: UNKNOWN
Platform: UNKNOWN
Classifier: Programming Language :: Python :: 3
Classifier: License :: OSI Approved :: GNU General Public License v3 or later (GPLv3+)
Classifier: Operating System :: OS Independent
Requires-Python: >=3.5
